odoo/addons/helpdesk_automove/CHANGELOG.md
odoo/addons/helpdesk_automove/README.rst
odoo/addons/helpdesk_automove/__init__.py
odoo/addons/helpdesk_automove/__manifest__.py
odoo/addons/helpdesk_automove/data/helpdesk_automove_cron.xml
odoo/addons/helpdesk_automove/i18n/ca_ES.po
odoo/addons/helpdesk_automove/i18n/es.po
odoo/addons/helpdesk_automove/models/__init__.py
odoo/addons/helpdesk_automove/models/helpdesk_stage.py
odoo/addons/helpdesk_automove/static/description/icon.png
odoo/addons/helpdesk_automove/tests/__init__.py
odoo/addons/helpdesk_automove/tests/test_automove.py
odoo/addons/helpdesk_automove/views/helpdesk_ticket_stage_automove.xml
odoo_addon_helpdesk_automove-17.0.1.0.0.dist-info/METADATA
odoo_addon_helpdesk_automove-17.0.1.0.0.dist-info/WHEEL
odoo_addon_helpdesk_automove-17.0.1.0.0.dist-info/top_level.txt
odoo_addon_helpdesk_automove-17.0.1.0.0.dist-info/RECORD
