Metadata-Version: 2.1
Name: odoo-addon-helpdesk-automove
Version: 17.0.1.0.0
Requires-Python: >=3.10
Requires-Dist: odoo-addon-helpdesk_mgmt>=17.0dev,<17.1dev
Requires-Dist: odoo>=17.0a,<17.1dev
Summary: ODOO helpdesk customizations for social cooperatives. In this module we want to move our desk cards between stages with timming conditions.
Home-page: https://gitlab.com/somitcoop/erp-research/odoo-helpdesk
License: AGPL-3
Author: =?utf-8?q?Som_It_Cooperatiu_SCCL=2C_Som_Connexi=C3=B3_SCCL=2C_Odoo_Community_Association_=28OCA=29?=
Author-email: support@odoo-community.org
Classifier: Programming Language :: Python
Classifier: Framework :: Odoo
Classifier: Framework :: Odoo :: 17.0
Classifier: License :: OSI Approved :: GNU Affero General Public License v3
